LICENSE
MANIFEST.in
README.rst
RELEASES
setup.py
pyga/__init__.py
pyga/entities.py
pyga/exceptions.py
pyga/requests.py
pyga/utils.py
pyga_fc.egg-info/PKG-INFO
pyga_fc.egg-info/SOURCES.txt
pyga_fc.egg-info/dependency_links.txt
pyga_fc.egg-info/namespace_packages.txt
pyga_fc.egg-info/requires.txt
pyga_fc.egg-info/top_level.txt
tests/__init__.py
tests/ga.py
tests/serialize.py
tests/utils.py