Metadata-Version: 1.1
Name: pyga-fc
Version: 2.4.2
Summary: Server side implemenation of Google Analytics in Python.
Home-page: http://github.com/kra3/py-ga-mob/commit/73a74eb4485f407a09fa194cc06a3c0d3775c350
Author: Arun K.R.
Author-email: the1.arun@gmail.com
License: Simplified BSD
Keywords: google analytics  mobile serverside
Platform: UNKNOWN
Classifier: Intended Audience :: Developers
Classifier: License :: OSI Approved :: BSD License
Classifier: Environment :: Web Environment
Classifier: Development Status :: 5 - Production/Stable
Classifier: Programming Language :: Python
Classifier: Operating System :: OS Independent
Classifier: Topic :: Software Development :: Libraries :: Python Modules
Classifier: Topic :: Internet
Classifier: Topic :: Internet :: WWW/HTTP
Classifier: Topic :: Internet :: WWW/HTTP :: WSGI
